infoblox_client/__init__.py
infoblox_client/connector.py
infoblox_client/exceptions.py
infoblox_client/feature.py
infoblox_client/object_manager.py
infoblox_client/objects.py
infoblox_client/utils.py
infoblox_client-0.5.0.dist-info/AUTHORS.rst
infoblox_client-0.5.0.dist-info/LICENSE
infoblox_client-0.5.0.dist-info/METADATA
infoblox_client-0.5.0.dist-info/WHEEL
infoblox_client-0.5.0.dist-info/top_level.txt
infoblox_client-0.5.0.dist-info/RECORD
