Metadata-Version: 2.1
Name: infoblox-client
Version: 0.5.0
Summary: Client for interacting with Infoblox NIOS over WAPI
Home-page: https://github.com/infobloxopen/infoblox-client
Author: John Belamaric
Author-email: jbelamaric@infoblox.com
License: Apache
Keywords: infoblox-client
Platform: UNKNOWN
Classifier: Development Status :: 3 - Alpha
Classifier: Intended Audience :: Developers
Classifier: License :: OSI Approved :: Apache Software License
Classifier: Natural Language :: English
Classifier: Programming Language :: Python :: 2
Classifier: Programming Language :: Python :: 2.7
Classifier: Programming Language :: Python :: 3
Classifier: Programming Language :: Python :: 3.5
Classifier: Programming Language :: Python :: 3.6
Classifier: Programming Language :: Python :: 3.7
Classifier: Programming Language :: Python :: 3.8
Requires-Dist: six (>=1.11.0)
Requires-Dist: requests (>=2.5.2)
Requires-Dist: urllib3 (>=1.13)
Requires-Dist: oslo.serialization (>=1.4.0)
Requires-Dist: oslo.log (>=1.8.0)
Requires-Dist: setuptools (>=17.1)
